setup.py
bin/pinger
pinger/__init__.py
pinger/app.py
pinger/config.py
pinger/daemon.py
pinger/exceptions.py
pinger/workers.py
pinger.egg-info/PKG-INFO
pinger.egg-info/SOURCES.txt
pinger.egg-info/dependency_links.txt
pinger.egg-info/not-zip-safe
pinger.egg-info/requires.txt
pinger.egg-info/top_level.txt
pinger/ext/__init__.py
pinger/ext/variables.py
pinger/ext/plugins/__init__.py
pinger/ext/plugins/dummy.py
pinger/ext/plugins/log.py
pinger/ext/plugins/sqlite.py
pinger/ext/plugins/stdout.py