Metadata-Version: 1.1
Name: pinger
Version: 0.1.2
Summary: Website monitoring tool
Home-page: https://github.com/pedrospdc/pinger
Author: Pedro Palhares (pedrospdc)
Author-email: pedrospdc@gmail.com
License: MIT
Download-URL: https://github.com/pedrospdc/pinger/tarball/0.1.2
Platform: UNKNOWN
Classifier: Development Status :: 3 - Alpha
Classifier: Environment :: Console
Classifier: Intended Audience :: Developers
Classifier: Operating System :: OS Independent
Classifier: Programming Language :: Python
